README.md
setup.cfg
setup.py
certbot_dns_websupportsk/__init__.py
certbot_dns_websupportsk/dns_websupportsk.py
certbot_dns_websupportsk.egg-info/PKG-INFO
certbot_dns_websupportsk.egg-info/SOURCES.txt
certbot_dns_websupportsk.egg-info/dependency_links.txt
certbot_dns_websupportsk.egg-info/entry_points.txt
certbot_dns_websupportsk.egg-info/requires.txt
certbot_dns_websupportsk.egg-info/top_level.txt