Metadata-Version: 2.1
Name: certbot-dns-websupportsk
Version: 0.1.6
Summary: Websupport DNS Authenticator plugin for Certbot
Home-page: https://github.com/JozefGalbicka/certbot-dns-websupportsk
Author: Jozef Galbicka
Author-email: alerts.cryp@gmail.com
License: MIT
Platform: UNKNOWN
Classifier: Development Status :: 3 - Alpha
Classifier: Environment :: Plugins
Classifier: Intended Audience :: System Administrators
Classifier: License :: OSI Approved :: MIT License
Classifier: Operating System :: POSIX :: Linux
Classifier: Programming Language :: Python
Classifier: Programming Language :: Python :: 3
Classifier: Programming Language :: Python :: 3.8
Classifier: Topic :: Internet :: WWW/HTTP
Classifier: Topic :: Security
Classifier: Topic :: System :: Installation/Setup
Classifier: Topic :: System :: Networking
Classifier: Topic :: System :: Systems Administration
Classifier: Topic :: Utilities
